RISC_V_CPU/EXE.v
module alu (
    input   wire    [31:0]  a,
    input   wire    [31:0]  b,
    input   wire    [4:0]   alu_ctrl,
    output  reg     [31:0]  result,
    output  wire            N, Z, C, V
);
    wire    [31:0]  b2,sum;
    wire            slt, sltu;

    assign b2 = alu_ctrl[4]? ~b : b;

    assign slt = N ^ V; 
    assign sltu = ~C;  

    always @(*) begin
        case (alu_ctrl[3:0])
            4'b0000: result <= sum;
            4'b0001: result <= a & b;
            4'b0010: result <= a | b;
            4'b0011: result <= a ^ b;
            4'b0100: result <= a << b[4:0];    
            4'b0101: result <= a >> b[4:0];    
            4'b0110: result <= a >>> b[4:0];   
            4'b0111: result <= {31'b0, slt};
            4'b1000: result <= {31'b0, sltu};
            default: result <= 32'b0;
        endcase
    end

    add_sub adder_subtractor (.a(a), .b(b2), .cin(alu_ctrl[4]), .sum(sum), .N(N), .Z(Z), .C(C), .V(V));

endmodule

module add_sub (
    input   wire    [31:0]  a,    
    input   wire    [31:0]  b,   
    input   wire            cin,
    output  wire    [31:0]  sum,
    output  wire            N, Z, C, V   
);
    wire    [31:0]  cout;

    adder_1bit bit31 (.a(a[31]), .b(b[31]), .cin(cout[30]), .sum(sum[31]), .cout(cout[31]));
    adder_1bit bit30 (.a(a[30]), .b(b[30]), .cin(cout[29]), .sum(sum[30]), .cout(cout[30]));
    adder_1bit bit29 (.a(a[29]), .b(b[29]), .cin(cout[28]), .sum(sum[29]), .cout(cout[29]));
    adder_1bit bit28 (.a(a[28]), .b(b[28]), .cin(cout[27]), .sum(sum[28]), .cout(cout[28]));

    adder_1bit bit27 (.a(a[27]), .b(b[27]), .cin(cout[26]), .sum(sum[27]), .cout(cout[27]));
    adder_1bit bit26 (.a(a[26]), .b(b[26]), .cin(cout[25]), .sum(sum[26]), .cout(cout[26]));
    adder_1bit bit25 (.a(a[25]), .b(b[25]), .cin(cout[24]), .sum(sum[25]), .cout(cout[25]));
    adder_1bit bit24 (.a(a[24]), .b(b[24]), .cin(cout[23]), .sum(sum[24]), .cout(cout[24]));

    adder_1bit bit23 (.a(a[23]), .b(b[23]), .cin(cout[22]), .sum(sum[23]), .cout(cout[23]));
    adder_1bit bit22 (.a(a[22]), .b(b[22]), .cin(cout[21]), .sum(sum[22]), .cout(cout[22]));
    adder_1bit bit21 (.a(a[21]), .b(b[21]), .cin(cout[20]), .sum(sum[21]), .cout(cout[21]));
    adder_1bit bit20 (.a(a[20]), .b(b[20]), .cin(cout[19]), .sum(sum[20]), .cout(cout[20]));

    adder_1bit bit19 (.a(a[19]), .b(b[19]), .cin(cout[18]), .sum(sum[19]), .cout(cout[19]));
    adder_1bit bit18 (.a(a[18]), .b(b[18]), .cin(cout[17]), .sum(sum[18]), .cout(cout[18]));
    adder_1bit bit17 (.a(a[17]), .b(b[17]), .cin(cout[16]), .sum(sum[17]), .cout(cout[17]));
    adder_1bit bit16 (.a(a[16]), .b(b[16]), .cin(cout[15]), .sum(sum[16]), .cout(cout[16]));

    adder_1bit bit15 (.a(a[15]), .b(b[15]), .cin(cout[14]), .sum(sum[15]), .cout(cout[15]));
    adder_1bit bit14 (.a(a[14]), .b(b[14]), .cin(cout[13]), .sum(sum[14]), .cout(cout[14]));
    adder_1bit bit13 (.a(a[13]), .b(b[13]), .cin(cout[12]), .sum(sum[13]), .cout(cout[13]));
    adder_1bit bit12 (.a(a[12]), .b(b[12]), .cin(cout[11]), .sum(sum[12]), .cout(cout[12]));

    adder_1bit bit11 (.a(a[11]), .b(b[11]), .cin(cout[10]), .sum(sum[11]), .cout(cout[11]));
    adder_1bit bit10 (.a(a[10]), .b(b[10]), .cin(cout[9]), .sum(sum[10]), .cout(cout[10]));
    adder_1bit bit09 (.a(a[9]), .b(b[9]), .cin(cout[8]), .sum(sum[9]), .cout(cout[9]));
    adder_1bit bit08 (.a(a[8]), .b(b[8]), .cin(cout[7]), .sum(sum[8]), .cout(cout[8]));

    adder_1bit bit07 (.a(a[7]), .b(b[7]), .cin(cout[6]), .sum(sum[7]), .cout(cout[7]));
    adder_1bit bit06 (.a(a[6]), .b(b[6]), .cin(cout[5]), .sum(sum[6]), .cout(cout[6]));
    adder_1bit bit05 (.a(a[5]), .b(b[5]), .cin(cout[4]), .sum(sum[5]), .cout(cout[5]));
    adder_1bit bit04 (.a(a[4]), .b(b[4]), .cin(cout[3]), .sum(sum[4]), .cout(cout[4]));

    adder_1bit bit03 (.a(a[3]), .b(b[3]), .cin(cout[2]), .sum(sum[3]), .cout(cout[3]));
    adder_1bit bit02 (.a(a[2]), .b(b[2]), .cin(cout[1]), .sum(sum[2]), .cout(cout[2]));
    adder_1bit bit01 (.a(a[1]), .b(b[1]), .cin(cout[0]), .sum(sum[1]), .cout(cout[1]));
    adder_1bit bit00 (.a(a[0]), .b(b[0]), .cin(cin), .sum(sum[0]), .cout(cout[0]));

    assign N = sum[31];
    assign Z = ~(|sum); //(sum == 32'b0);
    assign C = cout[31];
    assign V = cout[31] ^ cout[30];

endmodule

module adder_1bit(
    input   wire    a,
    input   wire    b,
    input   wire    cin,
    output  wire    sum,
    output  wire    cout
);
    assign sum = a ^ b ^ cin;
    assign cout = (a & b) | (a & cin) | (b & cin);
endmodule

RISC_V_CPU/tb_alu.v
`timescale 1ns/1ps

module tb_alu;
    reg     [31:0]  a, b;
    reg     [4:0]   alu_ctrl;
    wire    [31:0]  result;
    wire             N, Z, C, V;

alu u0 (.a(a), .b(b), .alu_ctrl(alu_ctrl), .result(result), .N(N), .Z(Z), .C(C), .V(V));

    initial begin
            
            a = 32'hf0000000;
            b = 32'h90000000;
            alu_ctrl = 5'b00000;
        #10 alu_ctrl = 5'b00001; 
        #10 alu_ctrl = 5'b00010; 
        #10 alu_ctrl = 5'b00011; 
        #10 alu_ctrl = 5'b00100; 
        #10 alu_ctrl = 5'b00101; 
        #10 alu_ctrl = 5'b00110; 
        #10 alu_ctrl = 5'b00111; 
        #10 alu_ctrl = 5'b01000; 

        #10 a = 32'h00000000;
            b = 32'h00000000;
            alu_ctrl = 5'b00000;
        #10 alu_ctrl = 5'b00001; 
        #10 alu_ctrl = 5'b00010; 
        #10 alu_ctrl = 5'b00011; 
        #10 alu_ctrl = 5'b00100; 
        #10 alu_ctrl = 5'b00101; 
        #10 alu_ctrl = 5'b00110; 
        #10 alu_ctrl = 5'b00111;    
        #10 alu_ctrl = 5'b01000;  

        #10 a = 32'h004400ff;
            b = 32'hf0000fff;
            alu_ctrl = 5'b00000;
        #10 alu_ctrl = 5'b00001; 
        #10 alu_ctrl = 5'b00010; 
        #10 alu_ctrl = 5'b00011; 
        #10 alu_ctrl = 5'b00100; 
        #10 alu_ctrl = 5'b00101; 
        #10 alu_ctrl = 5'b00110; 
        #10 alu_ctrl = 5'b00111; 
        #10 alu_ctrl = 5'b01000;       

        #10 a = 32'h00000419;
            b = 32'h00040004;
            alu_ctrl = 5'b00000;
        #10 alu_ctrl = 5'b00001; 
        #10 alu_ctrl = 5'b00010; 
        #10 alu_ctrl = 5'b00011; 
        #10 alu_ctrl = 5'b00100; 
        #10 alu_ctrl = 5'b00101; 
        #10 alu_ctrl = 5'b00110; 
        #10 alu_ctrl = 5'b00111; 
        #10 alu_ctrl = 5'b01000;     

        #10 a = 32'hf00fffff;
            b = 32'h80008000;
            alu_ctrl = 5'b00000;
        #10 alu_ctrl = 5'b00001; 
        #10 alu_ctrl = 5'b00010; 
        #10 alu_ctrl = 5'b00011; 
        #10 alu_ctrl = 5'b00100; 
        #10 alu_ctrl = 5'b00101; 
        #10 alu_ctrl = 5'b00110; 
        #10 alu_ctrl = 5'b00111; 
        #10 alu_ctrl = 5'b01000;     
    end

    initial begin
        $dumpfile("tb_alu.vcd");
        $dumpvars(0, tb_alu);
        $dumpflush;
        #600
        $finish;    
    end
endmodule

RISC_V_CPU/build/tb_alu.vcd
$date
	Tue Jul 16 01:49:06 2024
$end
$version
	Icarus Verilog
$end
$timescale
	1ps
$end
$scope module tb_alu $end
$var wire 32 ! result [31:0] $end
$var wire 1 " Z $end
$var wire 1 # V $end
$var wire 1 $ N $end
$var wire 1 % C $end
$var reg 32 & a [31:0] $end
$var reg 5 ' alu_ctrl [4:0] $end
$var reg 32 ( b [31:0] $end
$scope module u0 $end
$var wire 32 ) a [31:0] $end
$var wire 5 * alu_ctrl [4:0] $end
$var wire 32 + b [31:0] $end
$var wire 1 , slt $end
$var wire 1 - sltu $end
$var wire 32 . sum [31:0] $end
$var wire 32 / b2 [31:0] $end
$var wire 1 " Z $end
$var wire 1 # V $end
$var wire 1 $ N $end
$var wire 1 % C $end
$var reg 32 0 result [31:0] $end
$scope module adder_subtractor $end
$var wire 1 # V $end
$var wire 1 " Z $end
$var wire 32 1 a [31:0] $end
$var wire 32 2 b [31:0] $end
$var wire 1 3 cin $end
$var wire 32 4 sum [31:0] $end
$var wire 32 5 cout [31:0] $end
$var wire 1 $ N $end
$var wire 1 % C $end
$scope module bit00 $end
$var wire 1 6 a $end
$var wire 1 7 b $end
$var wire 1 3 cin $end
$var wire 1 8 cout $end
$var wire 1 9 sum $end
$upscope $end
$scope module bit01 $end
$var wire 1 : a $end
$var wire 1 ; b $end
$var wire 1 < cin $end
$var wire 1 = cout $end
$var wire 1 > sum $end
$upscope $end
$scope module bit02 $end
$var wire 1 ? a $end
$var wire 1 @ b $end
$var wire 1 A cin $end
$var wire 1 B cout $end
$var wire 1 C sum $end
$upscope $end
$scope module bit03 $end
$var wire 1 D a $end
$var wire 1 E b $end
$var wire 1 F cin $end
$var wire 1 G cout $end
$var wire 1 H sum $end
$upscope $end
$scope module bit04 $end
$var wire 1 I a $end
$var wire 1 J b $end
$var wire 1 K cin $end
$var wire 1 L cout $end
$var wire 1 M sum $end
$upscope $end
$scope module bit05 $end
$var wire 1 N a $end
$var wire 1 O b $end
$var wire 1 P cin $end
$var wire 1 Q cout $end
$var wire 1 R sum $end
$upscope $end
$scope module bit06 $end
$var wire 1 S a $end
$var wire 1 T b $end
$var wire 1 U cin $end
$var wire 1 V cout $end
$var wire 1 W sum $end
$upscope $end
$scope module bit07 $end
$var wire 1 X a $end
$var wire 1 Y b $end
$var wire 1 Z cin $end
$var wire 1 [ cout $end
$var wire 1 \ sum $end
$upscope $end
$scope module bit08 $end
$var wire 1 ] a $end
$var wire 1 ^ b $end
$var wire 1 _ cin $end
$var wire 1 ` cout $end
$var wire 1 a sum $end
$upscope $end
$scope module bit09 $end
$var wire 1 b a $end
$var wire 1 c b $end
$var wire 1 d cin $end
$var wire 1 e cout $end
$var wire 1 f sum $end
$upscope $end
$scope module bit10 $end
$var wire 1 g a $end
$var wire 1 h b $end
$var wire 1 i cin $end
$var wire 1 j cout $end
$var wire 1 k sum $end
$upscope $end
$scope module bit11 $end
$var wire 1 l a $end
$var wire 1 m b $end
$var wire 1 n cin $end
$var wire 1 o cout $end
$var wire 1 p sum $end
$upscope $end
$scope module bit12 $end
$var wire 1 q a $end
$var wire 1 r b $end
$var wire 1 s cin $end
$var wire 1 t cout $end
$var wire 1 u sum $end
$upscope $end
$scope module bit13 $end
$var wire 1 v a $end
$var wire 1 w b $end
$var wire 1 x cin $end
$var wire 1 y cout $end
$var wire 1 z sum $end
$upscope $end
$scope module bit14 $end
$var wire 1 { a $end
$var wire 1 | b $end
$var wire 1 } cin $end
$var wire 1 ~ cout $end
$var wire 1 !" sum $end
$upscope $end
$scope module bit15 $end
$var wire 1 "" a $end
$var wire 1 #" b $end
$var wire 1 $" cin $end
$var wire 1 %" cout $end
$var wire 1 &" sum $end
$upscope $end
$scope module bit16 $end
$var wire 1 '" a $end
$var wire 1 (" b $end
$var wire 1 )" cin $end
$var wire 1 *" cout $end
$var wire 1 +" sum $end
$upscope $end
$scope module bit17 $end
$var wire 1 ," a $end
$var wire 1 -" b $end
$var wire 1 ." cin $end
$var wire 1 /" cout $end
$var wire 1 0" sum $end
$upscope $end
$scope module bit18 $end
$var wire 1 1" a $end
$var wire 1 2" b $end
$var wire 1 3" cin $end
$var wire 1 4" cout $end
$var wire 1 5" sum $end
$upscope $end
$scope module bit19 $end
$var wire 1 6" a $end
$var wire 1 7" b $end
$var wire 1 8" cin $end
$var wire 1 9" cout $end
$var wire 1 :" sum $end
$upscope $end
$scope module bit20 $end
$var wire 1 ;" a $end
$var wire 1 <" b $end
$var wire 1 =" cin $end
$var wire 1 >" cout $end
$var wire 1 ?" sum $end
$upscope $end
$scope module bit21 $end
$var wire 1 @" a $end
$var wire 1 A" b $end
$var wire 1 B" cin $end
$var wire 1 C" cout $end
$var wire 1 D" sum $end
$upscope $end
$scope module bit22 $end
$var wire 1 E" a $end
$var wire 1 F" b $end
$var wire 1 G" cin $end
$var wire 1 H" cout $end
$var wire 1 I" sum $end
$upscope $end
$scope module bit23 $end
$var wire 1 J" a $end
$var wire 1 K" b $end
$var wire 1 L" cin $end
$var wire 1 M" cout $end
$var wire 1 N" sum $end
$upscope $end
$scope module bit24 $end
$var wire 1 O" a $end
$var wire 1 P" b $end
$var wire 1 Q" cin $end
$var wire 1 R" cout $end
$var wire 1 S" sum $end
$upscope $end
$scope module bit25 $end
$var wire 1 T" a $end
$var wire 1 U" b $end
$var wire 1 V" cin $end
$var wire 1 W" cout $end
$var wire 1 X" sum $end
$upscope $end
$scope module bit26 $end
$var wire 1 Y" a $end
$var wire 1 Z" b $end
$var wire 1 [" cin $end
$var wire 1 \" cout $end
$var wire 1 ]" sum $end
$upscope $end
$scope module bit27 $end
$var wire 1 ^" a $end
$var wire 1 _" b $end
$var wire 1 `" cin $end
$var wire 1 a" cout $end
$var wire 1 b" sum $end
$upscope $end
$scope module bit28 $end
$var wire 1 c" a $end
$var wire 1 d" b $end
$var wire 1 e" cin $end
$var wire 1 f" cout $end
$var wire 1 g" sum $end
$upscope $end
$scope module bit29 $end
$var wire 1 h" a $end
$var wire 1 i" b $end
$var wire 1 j" cin $end
$var wire 1 k" cout $end
$var wire 1 l" sum $end
$upscope $end
$scope module bit30 $end
$var wire 1 m" a $end
$var wire 1 n" b $end
$var wire 1 o" cin $end
$var wire 1 p" cout $end
$var wire 1 q" sum $end
$upscope $end
$scope module bit31 $end
$var wire 1 r" a $end
$var wire 1 s" b $end
$var wire 1 t" cin $end
$var wire 1 u" cout $end
$var wire 1 v" sum $end
$upscope $end
$upscope $end
$upscope $end
$upscope $end
$enddefinitions $end
$comment Show the parameter values. $end
$dumpall
$end
#0
$dumpvars
1v"
1u"
1t"
1s"
1r"
0q"
1p"
1o"
0n"
1m"
0l"
1k"
1j"
0i"
1h"
0g"
1f"
0e"
1d"
1c"
0b"
0a"
0`"
0_"
0^"
0]"
0\"
0["
0Z"
0Y"
0X"
0W"
0V"
0U"
0T"
0S"
0R"
0Q"
0P"
0O"
0N"
0M"
0L"
0K"
0J"
0I"
0H"
0G"
0F"
0E"
0D"
0C"
0B"
0A"
0@"
0?"
0>"
0="
0<"
0;"
0:"
09"
08"
07"
06"
05"
04"
03"
02"
01"
00"
0/"
0."
0-"
0,"
0+"
0*"
0)"
0("
0'"
0&"
0%"
0$"
0#"
0""
0!"
0~
0}
0|
0{
0z
0y
0x
0w
0v
0u
0t
0s
0r
0q
0p
0o
0n
0m
0l
0k
0j
0i
0h
0g
0f
0e
0d
0c
0b
0a
0`
0_
0^
0]
0\
0[
0Z
0Y
0X
0W
0V
0U
0T
0S
0R
0Q
0P
0O
0N
0M
0L
0K
0J
0I
0H
0G
0F
0E
0D
0C
0B
0A
0@
0?
0>
0=
0<
0;
0:
09
08
07
06
b11110000000000000000000000000000 5
b10000000000000000000000000000000 4
03
b10010000000000000000000000000000 2
b11110000000000000000000000000000 1
b10000000000000000000000000000000 0
b10010000000000000000000000000000 /
b10000000000000000000000000000000 .
0-
1,
b10010000000000000000000000000000 +
b0 *
b11110000000000000000000000000000 )
b10010000000000000000000000000000 (
b0 '
b11110000000000000000000000000000 &
1%
1$
0#
0"
b10000000000000000000000000000000 !
$end
#10000
b10010000000000000000000000000000 !
b10010000000000000000000000000000 0
b1 '
b1 *
#20000
b11110000000000000000000000000000 !
b11110000000000000000000000000000 0
b10 '
b10 *
#30000
b1100000000000000000000000000000 !
b1100000000000000000000000000000 0
b11 '
b11 *
#40000
b11110000000000000000000000000000 !
b11110000000000000000000000000000 0
b100 '
b100 *
#50000
b101 '
b101 *
#60000
b110 '
b110 *
#70000
b1 !
b1 0
b111 '
b111 *
#80000
b0 !
b0 0
b1000 '
b1000 *
#90000
b0 !
b0 0
1"
1-
0,
0%
0t"
0o"
0j"
0$
0u"
0p"
0k"
b0 5
0f"
0v"
0q"
0l"
b0 .
b0 4
0g"
0s"
0d"
b0 /
b0 2
0r"
0m"
0h"
0c"
b0 '
b0 *
b0 (
b0 +
b0 &
b0 )
b0 1
#100000
b1 '
b1 *
#110000
b10 '
b10 *
#120000
b11 '
b11 *
#130000
b100 '
b100 *
#140000
b101 '
b101 *
#150000
b110 '
b110 *
#160000
b111 '
b111 *
#170000
b1 !
b1 0
b1000 '
b1000 *
#180000
b11110000010001000001000011111110 !
b11110000010001000001000011111110 0
1u
1s
1o
1n
1j
1i
1e
1d
1`
1,
1_
1Z
1U
1P
1K
1F
1A
1<
1$
1[
1V
1Q
1L
1G
1B
1=
b111111111111 5
18
1v"
1q"
1l"
1g"
0p
0k
0f
0a
0"
1I"
15"
1\
1W
1R
1M
1H
1C
1>
b11110000010001000001000011111110 .
b11110000010001000001000011111110 4
09
1s"
1n"
1i"
1d"
1m
1h
1c
1^
1Y
1T
1O
1J
1E
1@
1;
17
b11110000000000000000111111111111 /
b11110000000000000000111111111111 2
1E"
11"
1X
1S
1N
1I
1D
1?
1:
16
b0 '
b0 *
b11110000000000000000111111111111 (
b11110000000000000000111111111111 +
b10001000000000011111111 &
b10001000000000011111111 )
b10001000000000011111111 1
#190000
b11111111 !
b11111111 0
b1 '
b1 *
#200000
b11110000010001000000111111111111 !
b11110000010001000000111111111111 0
b10 '
b10 *
#210000
b11110000010001000000111100000000 !
b11110000010001000000111100000000 0
b11 '
b11 *
#220000
b10000000000000000000000000000000 !
b10000000000000000000000000000000 0
b100 '
b100 *
#230000
b0 !
b0 0
b101 '
b101 *
#240000
b110 '
b110 *
#250000
b1 !
b1 0
b111 '
b111 *
#260000
b1000 '
b1000 *
#270000
b1000000010000011101 !
b1000000010000011101 0
0P
0L
0K
0G
0n
0j
0F
0B
0,
0u
0<
0$
0s
0i
0d
08
0_
0Z
0U
0A
0v"
0q"
0l"
0g"
0p
0o
0f
0e
0a
0`
1M
1H
19
0[
0V
0Q
b0 5
0=
0I"
15"
1k
0\
0W
0R
1C
b1000000010000011101 .
b1000000010000011101 4
0>
0s"
0n"
0i"
0d"
12"
0m
0h
0c
0^
0Y
0T
0O
0J
0E
0;
07
b1000000000000000100 /
b1000000000000000100 2
0E"
01"
1g
0X
0S
0N
0?
0:
b0 '
b0 *
b1000000000000000100 (
b1000000000000000100 +
b10000011001 &
b10000011001 )
b10000011001 1
#280000
b0 !
b0 0
b1 '
b1 *
#290000
b1000000010000011101 !
b1000000010000011101 0
b10 '
b10 *
#300000
b11 '
b11 *
#310000
b100000110010000 !
b100000110010000 0
b100 '
b100 *
#320000
b1000001 !
b1000001 0
b101 '
b101 *
#330000
b110 '
b110 *
#340000
b0 !
b0 0
b111 '
b111 *
#350000
b1 !
b1 0
b1000 '
b1000 *
#360000
b1110000000100000111111111111111 !
b1110000000100000111111111111111 0
0$"
0~
0}
0y
0x
0t
0s
0o
0n
0j
1k
0i
0e
0d
0`
0_
0[
0Z
0V
0U
0Q
13"
1/"
0P
0L
1."
1?"
1M
1*"
1="
0K
19"
0G
0-
1#
1%
1)"
1H
1u"
1%"
1,
18"
0F
0$
14"
b10000000000011111000000000000000 5
0B
0v"
1q"
1l"
1g"
0:"
05"
00"
0+"
0&"
1!"
1z
1u
1p
1f
1a
1\
1W
1R
1C
b1110000000100000111111111111111 .
b1110000000100000111111111111111 4
1>
1s"
02"
1#"
0@
b10000000000000001000000000000000 /
b10000000000000001000000000000000 2
1r"
1m"
1h"
1c"
16"
11"
1,"
1'"
1""
1{
1v
1q
1l
1b
1]
1X
1S
1N
1?
1:
b0 '
b0 *
b10000000000000001000000000000000 (
b10000000000000001000000000000000 +
b11110000000011111111111111111111 &
b11110000000011111111111111111111 )
b11110000000011111111111111111111 1
#370000
b10000000000000001000000000000000 !
b10000000000000001000000000000000 0
b1 '
b1 *
#380000
b11110000000011111111111111111111 !
b11110000000011111111111111111111 0
b10 '
b10 *
#390000
b1110000000011110111111111111111 !
b1110000000011110111111111111111 0
b11 '
b11 *
#400000
b11110000000011111111111111111111 !
b11110000000011111111111111111111 0
b100 '
b100 *
#410000
b101 '
b101 *
#420000
b110 '
b110 *
#430000
b1 !
b1 0
b111 '
b111 *
#440000
b0 !
b0 0
b1000 '
b1000 *
