RISC_V_CPU/IF.v

module IF(
    input   wire                i_clk,
    input   wire                i_rstn,
    input   wire                i_btaken,
    input   wire                i_jal,
    input   wire    [31:0]      i_imm_i,
    input   wire    [31:0]      i_imm_j,
    output  wire    [31:0]      o_jal_addr,
    output  wire    [31:0]      o_inst
);
    wire    clk     =   i_clk;
    wire    rstn    =   i_rstn;
    wire    [31:0]      i_pc;
    wire    [31:0]      o_pc;
    wire    [31:0]      next_pc;

    wire    [31:0]      imm_i = (i_imm_i << 1);
    wire    [31:0]      imm_j = (i_imm_j << 1);

    wire    [31:0]      imm_i_offset = i_imm_i + o_pc;
    wire    [31:0]      imm_j_offset = i_imm_j + o_pc;

    wire    [31:0]      btaken = i_btaken ? imm_i_offset : next_pc;
    wire    [31:0]      jal    = i_jal    ? imm_j_offset : btaken;
    assign              i_pc = jal; 

    assign              o_jal_addr = next_pc;

    pc program_counter(
        .clk        (clk    ),
        .rstn       (rstn   ),
        .i_pc       (i_pc   ),
        .o_pc       (o_pc   ),
        .o_next_pc  (next_pc)
    );

    inst_memory INST (
        .clk         (clk    ),       
        .we          (1'b0   ),      
        .addr        (o_pc   ),      
        .write_data  (32'h0  ),
        .read_data   (o_inst )
    );

endmodule

module pc(
    input   wire                clk,
    input   wire                rstn,
    input   wire    [31:0]      i_pc,
    output  reg     [31:0]      o_pc,
    output  reg     [31:0]      o_next_pc
);
    always @(posedge clk, negedge rstn) begin
        if (~rstn)  begin
            o_pc        <=  32'h0;
            o_next_pc   <=  32'h0;
        end
        else    begin
            o_pc        <=  i_pc;
            o_next_pc   <=  i_pc + 4;
        end
    end
endmodule



module inst_memory (
    input   wire                clk,       
    input   wire                we,      
    input   wire    [31:0]      addr,      
    input   wire    [31:0]      write_data,
    output  reg     [31:0]      read_data  
);

    reg [31:0] memory [0:255];

    initial begin
        $readmemh("inst_mem.mem", memory, 0, 255);
    end

    always @(posedge clk) begin
        if (we) begin
            memory[addr[9:2]] <= write_data;  
        end
    end

    always @(*) begin
        read_data = memory[addr[9:2]];        
    end

endmodule

RISC_V_CPU/tb_IF.v
`timescale 1ns/1ps
`include "IF.v"

module tb_IF;

    reg             clk;
    reg             rstn;
    reg             btaken;
    reg             jal;
    reg    [31:0]   imm_i;
    reg    [31:0]   imm_j;
    wire   [31:0]   jal_addr;
    wire   [31:0]   inst;

initial begin
    clk = 0;
    forever #5
    clk = ~clk;
end

initial begin
    rstn = 0;
#10
    rstn = 1;
end

initial begin
    btaken = 0;
    jal = 0;
    imm_i = 32'h1;
    imm_j = 32'h2;
end

IF instuction_fetch(
    .i_clk              (clk),
    .i_rstn             (rstn),
    .i_btaken           (btaken),
    .i_jal              (jal),
    .i_imm_i            (imm_i),
    .i_imm_j            (imm_j),
    .o_jal_addr         (jal_addr),
    .o_inst             (inst)
);

initial begin
    $dumpfile("tb_IF.vcd");
    $dumpvars(0, tb_IF);
    #100
    $finish;
end

endmodule

RISC_V_CPU/sim/tb_IF.vcd
$date
	Wed Jul 24 16:05:57 2024
$end
$version
	Icarus Verilog
$end
$timescale
	1ps
$end
$scope module tb_IF $end
$var wire 32 ! jal_addr [31:0] $end
$var wire 32 " inst [31:0] $end
$var reg 1 # btaken $end
$var reg 1 $ clk $end
$var reg 32 % imm_i [31:0] $end
$var reg 32 & imm_j [31:0] $end
$var reg 1 ' jal $end
$var reg 1 ( rstn $end
$scope module instuction_fetch $end
$var wire 1 ) clk $end
$var wire 1 # i_btaken $end
$var wire 1 $ i_clk $end
$var wire 32 * i_imm_i [31:0] $end
$var wire 32 + i_imm_j [31:0] $end
$var wire 1 ' i_jal $end
$var wire 32 , i_pc [31:0] $end
$var wire 1 ( i_rstn $end
$var wire 32 - o_jal_addr [31:0] $end
$var wire 1 . rstn $end
$var wire 32 / o_pc [31:0] $end
$var wire 32 0 o_inst [31:0] $end
$var wire 32 1 next_pc [31:0] $end
$var wire 32 2 jal [31:0] $end
$var wire 32 3 imm_j_offset [31:0] $end
$var wire 32 4 imm_j [31:0] $end
$var wire 32 5 imm_i_offset [31:0] $end
$var wire 32 6 imm_i [31:0] $end
$var wire 32 7 btaken [31:0] $end
$scope module INST $end
$var wire 1 ) clk $end
$var wire 1 8 we $end
$var wire 32 9 write_data [31:0] $end
$var wire 32 : addr [31:0] $end
$var reg 32 ; read_data [31:0] $end
$upscope $end
$scope module program_counter $end
$var wire 1 ) clk $end
$var wire 32 < i_pc [31:0] $end
$var wire 1 . rstn $end
$var reg 32 = o_next_pc [31:0] $end
$var reg 32 > o_pc [31:0] $end
$upscope $end
$upscope $end
$upscope $end
$enddefinitions $end
$comment Show the parameter values. $end
$dumpall
$end
#0
$dumpvars
b0 >
b0 =
b0 <
bx ;
b0 :
b0 9
08
b0 7
b10 6
b1 5
b100 4
b10 3
b0 2
b0 1
bx 0
b0 /
0.
b0 -
b0 ,
b10 +
b1 *
0)
0(
0'
b10 &
b1 %
0$
0#
bx "
b0 !
$end
#5000
1)
1$
#10000
0)
0$
1.
1(
#15000
b100 ,
b100 <
b100 2
b100 7
b100 !
b100 -
b100 1
b100 =
1)
1$
#20000
0)
0$
#25000
b1000 ,
b1000 <
b1000 2
b1000 7
b1000 !
b1000 -
b1000 1
b1000 =
b110 3
b101 5
b100 /
b100 :
b100 >
1)
1$
#30000
0)
0$
#35000
b1100 ,
b1100 <
b1100 2
b1100 7
b1100 !
b1100 -
b1100 1
b1100 =
b1010 3
b1001 5
b1000 /
b1000 :
b1000 >
1)
1$
#40000
0)
0$
#45000
b10000 ,
b10000 <
b10000 2
b10000 7
b10000 !
b10000 -
b10000 1
b10000 =
b1110 3
b1101 5
b1100 /
b1100 :
b1100 >
1)
1$
#50000
0)
0$
#55000
b10100 ,
b10100 <
b10100 2
b10100 7
b10100 !
b10100 -
b10100 1
b10100 =
b10010 3
b10001 5
b10000 /
b10000 :
b10000 >
1)
1$
#60000
0)
0$
#65000
b11000 ,
b11000 <
b11000 2
b11000 7
b11000 !
b11000 -
b11000 1
b11000 =
b10110 3
b10101 5
b10100 /
b10100 :
b10100 >
1)
1$
#70000
0)
0$
#75000
b11100 ,
b11100 <
b11100 2
b11100 7
b11100 !
b11100 -
b11100 1
b11100 =
b11010 3
b11001 5
b11000 /
b11000 :
b11000 >
1)
1$
#80000
0)
0$
#85000
b100000 ,
b100000 <
b100000 2
b100000 7
b100000 !
b100000 -
b100000 1
b100000 =
b11110 3
b11101 5
b11100 /
b11100 :
b11100 >
1)
1$
#90000
0)
0$
#95000
b100100 ,
b100100 <
b100100 2
b100100 7
b100100 !
b100100 -
b100100 1
b100100 =
b100010 3
b100001 5
b100000 /
b100000 :
b100000 >
1)
1$
