test/VGA_INT_GEN.v
module VGA_INT_GEN (
	input			CLK,
	input			RST,
	input			text_in,
	input	[7:0]	text,
	output		    vga_irq
);

localparam x = 2'b00;
localparam k = 2'b01;
localparam e = 2'b10;
localparam y = 2'b11;

reg [1:0]	cur_state;
reg [1:0]	nxt_state;

always @(posedge CLK, posedge RST)
	if(RST)
		cur_state <= 2'b00;
	else
		cur_state <= nxt_state;
		
always @(*)
	case({text_in, text, cur_state})
		{1'b1, 8'h4B, 2'b00} : nxt_state = 2'b01;
		{1'b1, 8'h45, 2'b01} : nxt_state = 2'b10;
		{1'b1, 8'h59, 2'b10} : nxt_state = 2'b11;
		default : nxt_state = 2'b00;
	endcase
	
assign vga_irq = (cur_state == 2'b11);



endmodule

test/tb_VGA_INT_GEN.v
`timescale 1ns/10ps
`include "VGA_INT_GEN.v"

module tb_VGA_INT_GEN;

    reg    		clk;
    reg			rstn;
    reg			text_in;
    reg	[7:0]	text;
    wire		vga_irq;

initial begin
    clk = 0;
    forever #5
    clk = ~clk;
end

initial begin
    rstn = 1;
#10
    rstn = 0;
end

initial begin
    text_in = 1'b1;
    text = 8'hff;
    #30
    text = 8'h4b;
    #10
    text = 8'h45;
    #10
    text = 8'h59;
end

VGA_INT_GEN dut(
    .CLK        (clk),
    .RST        (rstn),
    .text_in    (text_in),
    .text       (text),
    .vga_irq    (vga_irq)
);

initial begin
    $dumpfile("tb_VGA_INT_GEN.vcd");
    $dumpvars(0, tb_VGA_INT_GEN);
    $dumpflush;
    #100
    $finish;
end

endmodule

RISC_V_CPU/sim/tb_VGA_INT_GEN.vcd
$date
	Mon Jul 29 14:13:18 2024
$end
$version
	Icarus Verilog
$end
$timescale
	10ps
$end
$scope module tb_VGA_INT_GEN $end
$var wire 1 ! vga_irq $end
$var reg 1 " clk $end
$var reg 1 # rstn $end
$var reg 8 $ text [7:0] $end
$var reg 1 % text_in $end
$scope module dut $end
$var wire 1 " CLK $end
$var wire 1 # RST $end
$var wire 8 & text [7:0] $end
$var wire 1 % text_in $end
$var wire 1 ! vga_irq $end
$var parameter 2 ' e $end
$var parameter 2 ( k $end
$var parameter 2 ) x $end
$var parameter 2 * y $end
$var reg 2 + cur_state [1:0] $end
$var reg 2 , nxt_state [1:0] $end
$upscope $end
$upscope $end
$enddefinitions $end
$comment Show the parameter values. $end
$dumpall
b11 *
b0 )
b1 (
b10 '
$end
#0
$dumpvars
b0 ,
b0 +
b11111111 &
1%
b11111111 $
1#
0"
0!
$end
#500
1"
#1000
0"
0#
#1500
1"
#2000
0"
#2500
1"
#3000
b1 ,
0"
b1001011 $
b1001011 &
#3500
b0 ,
b1 +
1"
#4000
b10 ,
0"
b1000101 $
b1000101 &
#4500
b0 ,
b10 +
1"
#5000
b11 ,
0"
b1011001 $
b1011001 &
#5500
b0 ,
1!
b11 +
1"
#6000
0"
#6500
0!
b0 +
1"
