RISC_V_CPU/test_adder.v
module test_adder (
    input       [7:0]       a,
    input       [7:0]       b,
    input                   sub,
    output      [7:0]       sum,
    output                  N,   // Negative flag
    output                  Z,   // Zero flag
    output                  C,   // Carry flag
    output                  V    // Overflow flag
);

    wire [7:0] b_eff;       // Effective B (B or ~B)
    wire [7:0] p, g;        // Generate and Propagate
    wire [7:0] c;           // Carry bits

    // Effective B calculation based on Sub signal
    assign b_eff = b ^ {32{sub}};  // XOR with Sub to get B or ~B

    // Generate and Propagate
    // Stage 0
    assign g = a & b_eff;   // Generate
    assign p = a ^ b_eff;   // Propagate

    // Combine multiple stages for Kogge-Stone logic
    wire    [7:0]  g1, p1, g2, p2, g3, p3, g4, p4, g5, p5;

    // Stage 1
    assign {g1[0], p1[0]} = {g[0], p[0]};
    gp s1_01(.g_cur(g[1]), .p_cur(p[1]), .g_pre(g[0]), .p_pre(p[0]), .g_out(g1[1]), .p_out(p1[1]));
    gp s1_02(.g_cur(g[2]), .p_cur(p[2]), .g_pre(g[1]), .p_pre(p[1]), .g_out(g1[2]), .p_out(p1[2]));
    gp s1_03(.g_cur(g[3]), .p_cur(p[3]), .g_pre(g[2]), .p_pre(p[2]), .g_out(g1[3]), .p_out(p1[3]));
    gp s1_04(.g_cur(g[4]), .p_cur(p[4]), .g_pre(g[3]), .p_pre(p[3]), .g_out(g1[4]), .p_out(p1[4]));
    gp s1_05(.g_cur(g[5]), .p_cur(p[5]), .g_pre(g[4]), .p_pre(p[4]), .g_out(g1[5]), .p_out(p1[5]));
    gp s1_06(.g_cur(g[6]), .p_cur(p[6]), .g_pre(g[5]), .p_pre(p[5]), .g_out(g1[6]), .p_out(p1[6]));
    gp s1_07(.g_cur(g[7]), .p_cur(p[7]), .g_pre(g[6]), .p_pre(p[6]), .g_out(g1[7]), .p_out(p1[7]));

    // Stage 2
    assign {g2[0], p2[0]} = {g1[0], p1[0]};
    assign {g2[1], p2[1]} = {g1[1], p1[1]};
    gp s2_01(.g_cur(g1[2]), .p_cur(p1[2]), .g_pre(g1[1]), .p_pre(p1[1]), .g_out(g2[2]), .p_out(p2[2]));
    gp s2_02(.g_cur(g1[3]), .p_cur(p1[3]), .g_pre(g1[2]), .p_pre(p1[2]), .g_out(g2[3]), .p_out(p2[3]));
    gp s2_03(.g_cur(g1[4]), .p_cur(p1[4]), .g_pre(g1[3]), .p_pre(p1[3]), .g_out(g2[4]), .p_out(p2[4]));
    gp s2_04(.g_cur(g1[5]), .p_cur(p1[5]), .g_pre(g1[4]), .p_pre(p1[4]), .g_out(g2[5]), .p_out(p2[5]));
    gp s2_05(.g_cur(g1[6]), .p_cur(p1[6]), .g_pre(g1[5]), .p_pre(p1[5]), .g_out(g2[6]), .p_out(p2[6]));
    gp s2_06(.g_cur(g1[7]), .p_cur(p1[7]), .g_pre(g1[6]), .p_pre(p1[6]), .g_out(g2[7]), .p_out(p2[7]));

    // Stage 3
    assign {g3[0], p3[0]} = {g2[0], p2[0]};
    assign {g3[1], p3[1]} = {g2[1], p2[1]};
    assign {g3[2], p3[2]} = {g2[2], p2[2]};
    assign {g3[3], p3[3]} = {g2[3], p2[3]};
    gp s3_01(.g_cur(g2[4]), .p_cur(p2[4]), .g_pre(g2[3]), .p_pre(p2[3]), .g_out(g3[4]), .p_out(p3[4]));
    gp s3_02(.g_cur(g2[5]), .p_cur(p2[5]), .g_pre(g2[4]), .p_pre(p2[4]), .g_out(g3[5]), .p_out(p3[5]));
    gp s3_03(.g_cur(g2[6]), .p_cur(p2[6]), .g_pre(g2[5]), .p_pre(p2[5]), .g_out(g3[6]), .p_out(p3[6]));
    gp s3_04(.g_cur(g2[7]), .p_cur(p2[7]), .g_pre(g2[6]), .p_pre(p2[6]), .g_out(g3[7]), .p_out(p3[7]));

    // Carry calculation
    assign c[0] = sub;
    c_gen carry_1(.g(g[1]), .p(p[1]), .c_pre(c[0]), .c(c[1]));
    c_gen carry_2(.g(g[2]), .p(p[2]), .c_pre(c[1]), .c(c[2]));
    c_gen carry_3(.g(g[3]), .p(p[3]), .c_pre(c[2]), .c(c[3]));
    c_gen carry_4(.g(g[4]), .p(p[4]), .c_pre(c[3]), .c(c[4]));
    c_gen carry_5(.g(g[5]), .p(p[5]), .c_pre(c[4]), .c(c[5]));
    c_gen carry_6(.g(g[6]), .p(p[6]), .c_pre(c[5]), .c(c[6]));
    c_gen carry_7(.g(g[7]), .p(p[7]), .c_pre(c[6]), .c(c[7]));

    // Sum calculation
    assign sum = p ^ c;

    // Flags
    assign N = sum[7];          // Negative flag
    assign Z = (sum == 8'b0);   // Zero flag
    assign C = c[7];             // Carry flag
    assign V = c[7] ^ c[7];  // Overflow flag

endmodule

module gp(
    input   wire    g_cur,
    input   wire    p_cur,
    input   wire    g_pre,
    input   wire    p_pre,
    output  wire    g_out,
    output  wire    p_out
);
    assign {g_out, p_out} = {(g_cur | (p_cur & g_pre)), (p_cur & p_pre)};
endmodule

module c_gen(
    input   wire    g,
    input   wire    p,
    input   wire    c_pre,
    output  wire    c
);
    assign c = g | (p & c_pre);
endmodule

RISC_V_CPU/tb_test_adder.v
module tb_test_adder;

    reg             clk;
    reg             rstn;
    reg     [7:0]   a,b;
    reg             sub;
    wire    [7:0]   sum;
    wire            N,Z,C,V;

initial begin
    clk = 0;
    forever #5
    clk = ~clk;
end

initial begin
    rstn = 0;
#10
    rstn = 1;
end

test_adder test(
    .a(a),
    .b(b),
    .sub(sub),
    .sum(sum),
    .N(N),
    .Z(Z),
    .C(C),
    .V(V)
);

initial begin
    a = 8'h55; b = 8'h44; sub = 1'b0; #10
    a = 8'hab; b = 8'h12; sub = 1'b0; #10
    a = 8'h44; b = 8'h11; sub = 1'b0; #10
    a = 8'h00; b = 8'h00; sub = 1'b0; #10
    a = 8'h01; b = 8'h10; sub = 1'b1; #10
    a = 8'hff; b = 8'h80; sub = 1'b1; #10
    a = 8'h78; b = 8'h34; sub = 1'b1; #10
    a = 8'h00; b = 8'h00; sub = 1'b1; 
end



initial begin
    $dumpfile("tb_test_adder.vcd");
    $dumpvars(0, tb_test_adder);
    $dumpflush;
    #100
    $finish;
end

endmodule

RISC_V_CPU/tb_test_adder.vcd
$date
	Tue Jul 16 19:38:01 2024
$end
$version
	Icarus Verilog
$end
$timescale
	1s
$end
$scope module tb_test_adder $end
$var wire 8 ! sum [7:0] $end
$var wire 1 " Z $end
$var wire 1 # V $end
$var wire 1 $ N $end
$var wire 1 % C $end
$var reg 8 & a [7:0] $end
$var reg 8 ' b [7:0] $end
$var reg 1 ( clk $end
$var reg 1 ) rstn $end
$var reg 1 * sub $end
$scope module test $end
$var wire 1 # V $end
$var wire 8 + a [7:0] $end
$var wire 8 , b [7:0] $end
$var wire 8 - g [7:0] $end
$var wire 8 . p [7:0] $end
$var wire 1 * sub $end
$var wire 8 / sum [7:0] $end
$var wire 8 0 p3 [7:0] $end
$var wire 8 1 p2 [7:0] $end
$var wire 8 2 p1 [7:0] $end
$var wire 8 3 g3 [7:0] $end
$var wire 8 4 g2 [7:0] $end
$var wire 8 5 g1 [7:0] $end
$var wire 8 6 c [7:0] $end
$var wire 8 7 b_eff [7:0] $end
$var wire 1 " Z $end
$var wire 1 $ N $end
$var wire 1 % C $end
$scope module carry_1 $end
$var wire 1 8 c $end
$var wire 1 9 c_pre $end
$var wire 1 : g $end
$var wire 1 ; p $end
$upscope $end
$scope module carry_2 $end
$var wire 1 < c $end
$var wire 1 = c_pre $end
$var wire 1 > g $end
$var wire 1 ? p $end
$upscope $end
$scope module carry_3 $end
$var wire 1 @ c $end
$var wire 1 A c_pre $end
$var wire 1 B g $end
$var wire 1 C p $end
$upscope $end
$scope module carry_4 $end
$var wire 1 D c $end
$var wire 1 E c_pre $end
$var wire 1 F g $end
$var wire 1 G p $end
$upscope $end
$scope module carry_5 $end
$var wire 1 H c $end
$var wire 1 I c_pre $end
$var wire 1 J g $end
$var wire 1 K p $end
$upscope $end
$scope module carry_6 $end
$var wire 1 L c $end
$var wire 1 M c_pre $end
$var wire 1 N g $end
$var wire 1 O p $end
$upscope $end
$scope module carry_7 $end
$var wire 1 P c $end
$var wire 1 Q c_pre $end
$var wire 1 R g $end
$var wire 1 S p $end
$upscope $end
$scope module s1_01 $end
$var wire 1 T g_cur $end
$var wire 1 U g_pre $end
$var wire 1 V p_cur $end
$var wire 1 W p_pre $end
$var wire 1 X p_out $end
$var wire 1 Y g_out $end
$upscope $end
$scope module s1_02 $end
$var wire 1 Z g_cur $end
$var wire 1 [ g_pre $end
$var wire 1 \ p_cur $end
$var wire 1 ] p_pre $end
$var wire 1 ^ p_out $end
$var wire 1 _ g_out $end
$upscope $end
$scope module s1_03 $end
$var wire 1 ` g_cur $end
$var wire 1 a g_pre $end
$var wire 1 b p_cur $end
$var wire 1 c p_pre $end
$var wire 1 d p_out $end
$var wire 1 e g_out $end
$upscope $end
$scope module s1_04 $end
$var wire 1 f g_cur $end
$var wire 1 g g_pre $end
$var wire 1 h p_cur $end
$var wire 1 i p_pre $end
$var wire 1 j p_out $end
$var wire 1 k g_out $end
$upscope $end
$scope module s1_05 $end
$var wire 1 l g_cur $end
$var wire 1 m g_pre $end
$var wire 1 n p_cur $end
$var wire 1 o p_pre $end
$var wire 1 p p_out $end
$var wire 1 q g_out $end
$upscope $end
$scope module s1_06 $end
$var wire 1 r g_cur $end
$var wire 1 s g_pre $end
$var wire 1 t p_cur $end
$var wire 1 u p_pre $end
$var wire 1 v p_out $end
$var wire 1 w g_out $end
$upscope $end
$scope module s1_07 $end
$var wire 1 x g_cur $end
$var wire 1 y g_pre $end
$var wire 1 z p_cur $end
$var wire 1 { p_pre $end
$var wire 1 | p_out $end
$var wire 1 } g_out $end
$upscope $end
$scope module s2_01 $end
$var wire 1 ~ g_cur $end
$var wire 1 !" g_pre $end
$var wire 1 "" p_cur $end
$var wire 1 #" p_pre $end
$var wire 1 $" p_out $end
$var wire 1 %" g_out $end
$upscope $end
$scope module s2_02 $end
$var wire 1 &" g_cur $end
$var wire 1 '" g_pre $end
$var wire 1 (" p_cur $end
$var wire 1 )" p_pre $end
$var wire 1 *" p_out $end
$var wire 1 +" g_out $end
$upscope $end
$scope module s2_03 $end
$var wire 1 ," g_cur $end
$var wire 1 -" g_pre $end
$var wire 1 ." p_cur $end
$var wire 1 /" p_pre $end
$var wire 1 0" p_out $end
$var wire 1 1" g_out $end
$upscope $end
$scope module s2_04 $end
$var wire 1 2" g_cur $end
$var wire 1 3" g_pre $end
$var wire 1 4" p_cur $end
$var wire 1 5" p_pre $end
$var wire 1 6" p_out $end
$var wire 1 7" g_out $end
$upscope $end
$scope module s2_05 $end
$var wire 1 8" g_cur $end
$var wire 1 9" g_pre $end
$var wire 1 :" p_cur $end
$var wire 1 ;" p_pre $end
$var wire 1 <" p_out $end
$var wire 1 =" g_out $end
$upscope $end
$scope module s2_06 $end
$var wire 1 >" g_cur $end
$var wire 1 ?" g_pre $end
$var wire 1 @" p_cur $end
$var wire 1 A" p_pre $end
$var wire 1 B" p_out $end
$var wire 1 C" g_out $end
$upscope $end
$scope module s3_01 $end
$var wire 1 D" g_cur $end
$var wire 1 E" g_pre $end
$var wire 1 F" p_cur $end
$var wire 1 G" p_pre $end
$var wire 1 H" p_out $end
$var wire 1 I" g_out $end
$upscope $end
$scope module s3_02 $end
$var wire 1 J" g_cur $end
$var wire 1 K" g_pre $end
$var wire 1 L" p_cur $end
$var wire 1 M" p_pre $end
$var wire 1 N" p_out $end
$var wire 1 O" g_out $end
$upscope $end
$scope module s3_03 $end
$var wire 1 P" g_cur $end
$var wire 1 Q" g_pre $end
$var wire 1 R" p_cur $end
$var wire 1 S" p_pre $end
$var wire 1 T" p_out $end
$var wire 1 U" g_out $end
$upscope $end
$scope module s3_04 $end
$var wire 1 V" g_cur $end
$var wire 1 W" g_pre $end
$var wire 1 X" p_cur $end
$var wire 1 Y" p_pre $end
$var wire 1 Z" p_out $end
$var wire 1 [" g_out $end
$upscope $end
$upscope $end
$upscope $end
$enddefinitions $end
$comment Show the parameter values. $end
$dumpall
$end
#0
$dumpvars
0["
0Z"
0Y"
0X"
1W"
0V"
1U"
0T"
0S"
0R"
0Q"
1P"
0O"
0N"
0M"
0L"
0K"
0J"
0I"
0H"
0G"
0F"
0E"
0D"
0C"
0B"
0A"
0@"
1?"
0>"
1="
0<"
0;"
0:"
09"
18"
07"
06"
05"
04"
03"
02"
01"
00"
0/"
0."
0-"
0,"
0+"
0*"
0)"
0("
1'"
0&"
1%"
0$"
0#"
0""
0!"
1~
0}
0|
0{
0z
1y
0x
1w
0v
0u
0t
0s
1r
0q
0p
1o
0n
0m
0l
0k
0j
0i
1h
0g
0f
0e
0d
0c
0b
1a
0`
1_
0^
0]
0\
0[
1Z
0Y
0X
1W
0V
0U
0T
0S
0R
1Q
0P
0O
1N
0M
1L
0K
0J
0I
0H
1G
0F
0E
0D
0C
0B
1A
0@
0?
1>
0=
1<
0;
0:
09
08
b1000100 7
b1000100 6
b1000100 5
b1000100 4
b1000100 3
b1 2
b1 1
b1 0
b1010101 /
b10001 .
b1000100 -
b1000100 ,
b1010101 +
0*
0)
0(
b1000100 '
b1010101 &
0%
0$
0#
0"
b1010101 !
$end
#5
1(
#10
1L"
1S"
0M
0U"
16"
0H
b10 3
0P"
0W"
b1 0
0G"
0X"
1."
15"
14"
1;"
0I
1!"
0%"
b10 4
0="
0$"
0*"
0B"
1j
1p
0D
1Y
1=
b100001 1
18
0~
0'"
08"
0?"
0#"
0""
0)"
0("
0/"
0:"
0A"
0@"
0E
0%
1T
1[
1:
0_
b10 5
0w
0A
0Q
0X
0^
0d
0v
b110001 2
0|
0@
0P
0<
b10 6
0L
1$
b10010 7
0Z
0a
0r
0y
0>
0N
b10111011 !
b10111011 /
0V
0\
0]
1b
0c
1h
1i
1n
1o
0t
1u
1z
0{
0;
0?
1C
1G
1K
0O
1S
b10 -
b10111001 .
0(
b10010 '
b10010 ,
b10101011 &
b10101011 +
1)
#15
1(
#20
b0 3
0L"
0S"
b1 0
06"
b0 4
0!"
b1 1
0""
0)"
0."
05"
04"
0;"
0A
b0 5
0Y
0=
0^
0j
0p
0<
b0 6
08
0$
b1 2
b10001 7
0T
0[
0:
b1010101 !
b1010101 /
0V
1W
1\
0]
0b
1c
0i
0n
1t
0u
0z
1{
0;
1?
0C
0K
1O
0S
b0 -
b1010101 .
0(
b10001 '
b10001 ,
b1000100 &
b1000100 +
#25
1(
#30
b0 0
b0 1
b0 2
1"
0W
0h
0o
0G
b0 7
b0 !
b0 /
0\
0c
0t
0{
0?
0O
b0 .
0(
b0 '
b0 ,
b0 &
b0 +
#35
1(
#40
1E
1@
1%"
1G"
1X"
1A
1*"
1B"
1<
b111 3
1!"
1""
1)"
1("
1/"
1:"
1A"
1@"
1=
b111 4
1Y
b1000 0
1^
1d
1v
1|
18
1$
b11 5
b10001000 1
0"
b11100001 !
b11100001 /
1V
1\
1]
1b
1c
1i
1n
1t
1u
1z
1{
1;
1?
1C
1K
1O
1S
1U
b1 -
b11001100 2
b11101111 7
0W
19
b11101110 .
0(
b1111 6
1*
b10000 '
b10000 ,
b1 &
b1 +
#45
1(
#50
1I"
1O"
1U"
1["
b11111111 3
b0 0
1D"
1K"
1E"
1J"
1Q"
1P"
1W"
1V"
0G"
11"
0X"
1+"
17"
1="
b11111111 4
1C"
0*"
b0 1
0B"
1,"
13"
1~
1'"
1&"
1-"
12"
19"
18"
1?"
1>"
0""
0)"
0("
0/"
1k
0:"
0A"
0@"
1I
1f
1m
1F
1_
1e
1q
1w
b11111111 5
1}
1M
1Q
1%
0^
0d
0v
b0 2
0|
1D
1H
1L
b11111111 6
1P
0$
b1111111 7
1T
1Z
1[
1`
1a
1g
1l
1r
1s
0x
1y
1:
1>
1B
1J
1N
0R
b1111111 !
b1111111 /
0V
0\
0]
0b
0c
0h
0i
0n
0o
0t
0u
1z
0{
0;
0?
0C
0G
0K
0O
1S
b1111111 -
b10000000 .
0(
b10000000 '
b10000000 ,
b11111111 &
b11111111 +
#55
1(
#60
1I"
1O"
1["
1D"
1K"
1J"
1Q"
11"
17"
1V"
1C"
14"
1;"
0A
1,"
13"
02"
09"
b11111000 3
0%"
b11 0
0$"
1p
0<
1k
0q
1I
1M
1>"
1D
1H
b11111000 4
0!"
0~
0'"
b11 1
1#"
0""
0)"
1}
1%
1h
1n
1o
1u
1G
1K
0f
0l
0m
0s
0F
0J
0Y
0_
1X
0^
b11111011 6
1P
b11011000 5
0$
b100011 2
b11001011 7
0T
0U
0Z
0[
0a
0:
0>
b1001000 !
b1001000 /
1V
1W
0\
1]
0c
1z
1;
0?
1S
b1001000 -
b10110011 .
0(
b110100 '
b110100 ,
b1111000 &
b1111000 +
#65
1(
#70
1"
1H"
1N"
1T"
1Z"
b11111111 0
0$
0["
0I"
0O"
1%
1G"
1F"
1M"
1L"
1S"
1R"
1Y"
1X"
0U"
1P
1$"
1*"
10"
16"
1<"
b11111111 1
1B"
b0 3
0V"
0D"
0K"
0J"
0Q"
0E"
0P"
0W"
0C"
01"
07"
1Q
1""
1)"
1("
1/"
1."
15"
1:"
1A"
1A
0+"
b0 4
0="
1L
1^
1d
1j
1v
1<
0>"
0,"
03"
0&"
0-"
08"
0?"
0}
0k
14"
1;"
1@"
1I
1M
1\
1c
1?
0e
b0 5
0w
1E
1p
b11111111 2
1|
1D
1H
b11111111 6
1@
b11111111 7
0`
0g
0r
0y
0B
0N
b0 !
b0 /
1b
1h
1i
1n
1o
1t
1u
1{
1C
1G
1K
1O
b0 -
b11111111 .
0(
b0 '
b0 ,
b0 &
b0 +
